{
  "id": "Javierrocadev_hard-cheetah-69",
  "name": "hard-cheetah-69",
  "category": "buttons",
  "author": "Javierrocadev",
  "description": "hard-cheetah-69 组件",
  "tags": [],
  "original": {
    "html": "<button class=\"relative border hover:border-sky-600 duration-500 group cursor-pointer text-sky-50  overflow-hidden h-14 w-56 rounded-md bg-sky-800 p-2 flex justify-center items-center font-extrabold\">\n  <div class=\"absolute z-10 w-48 h-48 rounded-full group-hover:scale-150 transition-all  duration-500 ease-in-out bg-sky-900 delay-150 group-hover:delay-75\"></div>\n  <div class=\"absolute z-10 w-40 h-40 rounded-full group-hover:scale-150 transition-all  duration-500 ease-in-out bg-sky-800 delay-150 group-hover:delay-100\"></div>\n  <div class=\"absolute z-10 w-32 h-32 rounded-full group-hover:scale-150 transition-all  duration-500 ease-in-out bg-sky-700 delay-150 group-hover:delay-150\"></div>\n  <div class=\"absolute z-10 w-24 h-24 rounded-full group-hover:scale-150 transition-all  duration-500 ease-in-out bg-sky-600 delay-150 group-hover:delay-200\"></div>\n  <div class=\"absolute z-10 w-16 h-16 rounded-full group-hover:scale-150 transition-all  duration-500 ease-in-out bg-sky-500 delay-150 group-hover:delay-300\"></div>\n  <p class=\"z-10\">Discover More</p>\n</button>",
    "css": "",
    "file_path": "/mnt/persist/workspace/Buttons/Javierrocadev_hard-cheetah-69.html"
  },
  "uniapp": {
    "template": "<button class=\"relative border hover:border-sky-600 duration-500 group cursor-pointer text-sky-50  overflow-hidden h-14 w-56 rounded-md bg-sky-800 p-2 flex justify-center items-center font-extrabold\"></button>\n  <view class=\"absolute z-10 w-48 h-48 rounded-full group-hover:scale-150 transition-all  duration-500 ease-in-out bg-sky-900 delay-150 group-hover:delay-75\"></view>\n  <view class=\"absolute z-10 w-40 h-40 rounded-full group-hover:scale-150 transition-all  duration-500 ease-in-out bg-sky-800 delay-150 group-hover:delay-100\"></view>\n  <view class=\"absolute z-10 w-32 h-32 rounded-full group-hover:scale-150 transition-all  duration-500 ease-in-out bg-sky-700 delay-150 group-hover:delay-150\"></view>\n  <view class=\"absolute z-10 w-24 h-24 rounded-full group-hover:scale-150 transition-all  duration-500 ease-in-out bg-sky-600 delay-150 group-hover:delay-200\"></view>\n  <view class=\"absolute z-10 w-16 h-16 rounded-full group-hover:scale-150 transition-all  duration-500 ease-in-out bg-sky-500 delay-150 group-hover:delay-300\"></view>\n  <text class=\"z-10\">Discover More</text>\n</button>",
    "script": "export default {\n  name: 'GalaxyHardCheetah69',\n  props: {\n    // 根据组件类型动态生成props\n  },\n  data() {\n    return {\n      // 组件状态\n    };\n  },\n  methods: {\n    // 组件方法\n  }\n}",
    "style": "",
    "component_name": "GalaxyHardCheetah69"
  },
  "platforms": {
    "h5": true,
    "mp-weixin": true,
    "mp-alipay": true,
    "mp-baidu": true,
    "mp-toutiao": true,
    "app-plus": true
  },
  "props": [
    {
      "name": "disabled",
      "type": "Boolean",
      "default": false,
      "required": false,
      "description": "是否禁用"
    },
    {
      "name": "text",
      "type": "String",
      "default": "按钮",
      "required": false,
      "description": "按钮文字"
    },
    {
      "name": "type",
      "type": "String",
      "default": "primary",
      "required": false,
      "description": "按钮类型"
    }
  ],
  "events": [
    {
      "name": "click",
      "description": "点击事件",
      "parameters": [
        "event"
      ]
    }
  ],
  "slots": [
    {
      "name": "",
      "description": "",
      "props": []
    }
  ],
  "compatibility": {
    "h5": {
      "supported": true,
      "issues": [],
      "alternatives": []
    },
    "mp-weixin": {
      "supported": true,
      "issues": [],
      "alternatives": []
    },
    "mp-alipay": {
      "supported": true,
      "issues": [],
      "alternatives": []
    },
    "app-plus": {
      "supported": true,
      "issues": [],
      "alternatives": []
    }
  },
  "performance": {
    "complexity": "low",
    "bundle_size": 1075,
    "render_cost": "low",
    "memory_usage": "low"
  },
  "dependencies": [],
  "examples": [
    {
      "title": "",
      "description": "",
      "code": ""
    }
  ],
  "created_at": "2025-07-31T07:55:33.408Z",
  "updated_at": "2025-07-31T07:55:33.408Z"
}